lovely_ctypes/__init__.py
lovely_ctypes/_modidx.py
lovely_ctypes/hexdump.py
lovely_ctypes/hexint.py
lovely_ctypes/utils.py
lovely_ctypes-0.0.1.dist-info/licenses/LICENSE
lovely_ctypes-0.0.1.dist-info/METADATA
lovely_ctypes-0.0.1.dist-info/WHEEL
lovely_ctypes-0.0.1.dist-info/entry_points.txt
lovely_ctypes-0.0.1.dist-info/top_level.txt
lovely_ctypes-0.0.1.dist-info/RECORD
